cipher/__init__.py
cipher/equation_cipher.py
cipher/equation_decipher.py
cipher/tests.py
cipher/time_handler.py
equation_cipher-2.0.0.dist-info/LICENCE
equation_cipher-2.0.0.dist-info/METADATA
equation_cipher-2.0.0.dist-info/WHEEL
equation_cipher-2.0.0.dist-info/top_level.txt
equation_cipher-2.0.0.dist-info/RECORD
