Metadata-Version: 2.1
Name: equation-cipher
Version: 2.0.0
Summary: An Encryption algorithm for encrypting any text.
Home-page: https://github.com/malhar-stories/equation_cipher
Author: Shounak Joshi
Author-email: shounakjoshi16@gmail.com
License: UNKNOWN
Platform: UNKNOWN
Classifier: Programming Language :: Python :: 3
Classifier: License :: OSI Approved :: MIT License
Classifier: Operating System :: OS Independent
